{
    "app-title": "قرآن مجید",

    "home-title": "قرآن مجید",
    "home-action-search": "جستجو",
    "home-drawer-account-name": "قرآن مجید",
    "home-drawer-account-email": "نسخه 1.23",
    "home-drawer-share": "به اشتراک گذاری",
    "home-drawer-help-and-support": "راهنما و پشتیبانی",
    "home-drawer-settings": "تنظیمات",
    "home-drawer-about": "درباره برنامه",
    "home-tab-chapters": "سوره‌ها",
    "home-tab-parts": "جزءها",
    "home-tab-bookmarks": "نشان‌شده‌ها",

    "chapter-details-action-share": "اشتراک گذاری",

    "search-title": "جستجو",

    "share-title": "به اشتراک گذاری",

    "help-and-support-title": "راهنما و پشتیبانی",

    "settings-title": "تنظیمات",
    
    "about-title": "درباره برنامه",

    "chapter-item-description": "${classification}، ${versesCount} آیه",
    "chapter-item-order": "ترتیب نزول ${order}",
    "chapter-item-part-number": "جزء ${partNumber}",

    "chapter-classification-meccan": "مکی",
    "chapter-classification-medinan": "مدنی"
}